{
  "anecdotes": [
    {
      "content": "scc",
      "id": "13435",
      "votes": 5
    },
    {
      "content": "Any fool can write code that a computer can understand. Good programmers write code that humans can understand.",
      "id": "36975",
      "votes": 28
    },
    {
      "content": "xcvxcvxcvxcvxcv",
      "votes": 4,
      "id": "vqzpP1R"
    },
    {
      "content": "sdfsdfsdf",
      "id": "66045",
      "votes": 5
    },
    {
      "content": "BCVBCVBCVB",
      "votes": 5,
      "id": "FX3K8tK"
    },
    {
      "content": "cvbcvbcvbcvbcvb",
      "id": "34463",
      "votes": 5
    },
    {
      "content": "zxczxcadasdasd",
      "votes": 5,
      "id": "oxcI_V1"
    },
    {
      "content": "CCCCC",
      "id": "69165",
      "votes": 5
    },
    {
      "content": "AWRAWRAWE",
      "votes": 5,
      "id": "Y_IKiDQ"
    },
    {
      "content": "RWRWERWER",
      "votes": 5,
      "id": "C9JNy-K"
    }
  ]
}